ubicoders_vrobots_ipc/__init__.py
ubicoders_vrobots_ipc/data_sync.py
ubicoders_vrobots_ipc/list_topics.py
ubicoders_vrobots_ipc/node_iox2.py
ubicoders_vrobots_ipc/node_iox2_utils.py
ubicoders_vrobots_ipc/node_zenoh.py
ubicoders_vrobots_ipc/rtg_pub.py
ubicoders_vrobots_ipc/rtg_sub.py
ubicoders_vrobots_ipc/srv_apis.py
ubicoders_vrobots_ipc/srv_base.py
ubicoders_vrobots_ipc/vrobot_client.py
ubicoders_vrobots_ipc/vrobot_node.py
ubicoders_vrobots_ipc/z_srv.py
ubicoders_vrobots_ipc/z_srv_client.py
ubicoders_vrobots_ipc-0.3.0.dist-info/licenses/LICENSE
ubicoders_vrobots_ipc-0.3.0.dist-info/METADATA
ubicoders_vrobots_ipc-0.3.0.dist-info/WHEEL
ubicoders_vrobots_ipc-0.3.0.dist-info/entry_points.txt
ubicoders_vrobots_ipc-0.3.0.dist-info/top_level.txt
ubicoders_vrobots_ipc-0.3.0.dist-info/RECORD
