Metadata-Version: 2.4
Name: ubicoders-vrobots-ipc
Version: 0.3.0
Summary: Ubicoders virtual robots IPC for PC
Author-email: Elliot Lee <info@ubicoders.com>
License: MIT
Project-URL: Homepage, https://github.com/ubicoders0/vrobots-ipc
Requires-Python: >=3.9
License-File: LICENSE
Requires-Dist: numpy
Requires-Dist: flatbuffers==23.5.26
Requires-Dist: fastapi
Requires-Dist: uvicorn
Requires-Dist: asyncio
Requires-Dist: requests
Requires-Dist: psutil
Requires-Dist: dash
Requires-Dist: plotly
Requires-Dist: colorama
Requires-Dist: matplotlib
Requires-Dist: pyqt5
Requires-Dist: pyqtgraph
Requires-Dist: pandas
Requires-Dist: scipy
Requires-Dist: ipython
Requires-Dist: ipykernel
Requires-Dist: jupyterlab
Requires-Dist: ipympl
Requires-Dist: iceoryx2==0.7.0
Requires-Dist: eclipse-zenoh==1.5.1
Requires-Dist: opencv-python
Requires-Dist: opencv-contrib-python
Requires-Dist: ubicoders-vrobots-msgs==2.0.2
Dynamic: license-file
